{
  "2023-05-21": {
    "Software Development": 14353,
    "Uncategorized": 3059,
    "Entertainment": 2379,
    "Utilities": 334,
    "Communication & Scheduling": 233,
    "Reference & Learning": 216,
    "Social Networking": 114
  },
  "2023-05-22": {
    "Entertainment": 7150,
    "Software Development": 5818,
    "Uncategorized": 2776,
    "Reference & Learning": 1865,
    "News & Opinion": 383,
    "Communication & Scheduling": 354,
    "Social Networking": 244,
    "Utilities": 193,
    "Shopping": 74,
    "Business": 5
  },
  "2023-05-23": {
    "Software Development": 155,
    "Entertainment": 2
  },
  "2023-05-24": {},
  "2023-05-25": {},
  "2023-05-26": {},
  "2023-05-27": {}
}