{
  "2022-09-18": {
    "Video": 8295,
    "Browsers": 6310,
    "Instant Message": 4945,
    "General Utilities": 1011,
    "Email": 707,
    "Voice Chat": 136,
    "General Business": 59,
    "Photos": 45,
    "Uncategorized": 37,
    "Intelligence": 25,
    "General Software Development": 9
  },
  "2022-09-19": {
    "Browsers": 16559,
    "Instant Message": 6509,
    "Video": 4453,
    "General Utilities": 1078,
    "General Shopping": 813,
    "Uncategorized": 558,
    "Voice Chat": 282,
    "General Reference & Learning": 193
  },
  "2022-09-20": {
    "General Utilities": 6261,
    "Browsers": 3727,
    "Instant Message": 3185,
    "Video": 1841,
    "Voice Chat": 441,
    "Uncategorized": 412,
    "Email": 176,
    "General Shopping": 99,
    "Photos": 6
  },
  "2022-09-21": {
    "Browsers": 5986,
    "Instant Message": 5061,
    "General Utilities": 4774,
    "General Shopping": 666,
    "Email": 354,
    "Uncategorized": 312,
    "Photos": 105,
    "Video": 33,
    "Voice Chat": 12
  },
  "2022-09-22": {
    "Video": 8611,
    "Instant Message": 4576,
    "General Utilities": 1031,
    "Browsers": 1014,
    "General Design & Composition": 535,
    "Voice Chat": 385,
    "Email": 152,
    "Search": 20,
    "General Reference & Learning": 7,
    "Uncategorized": 4
  },
  "2022-09-23": {
    "Browsers": 5737,
    "Instant Message": 3505,
    "Video": 2405,
    "General Utilities": 1392,
    "General Design & Composition": 1201,
    "General Communication & Scheduling": 326,
    "Uncategorized": 316,
    "Voice Chat": 256,
    "General Reference & Learning": 170,
    "Email": 123,
    "General Shopping": 118,
    "Search": 23,
    "Operations": 8,
    "General Software Development": 6
  },
  "2022-09-24": {
    "Instant Message": 647,
    "Browsers": 167,
    "General Utilities": 57
  }
}