[
  {
    "Rank": 1,
    "Time Spent (seconds)": 9519,
    "Number of People": 1,
    "Activity": "Firefox Android",
    "Category": "Browsers",
    "Productivity": 0
  },
  {
    "Rank": 2,
    "Time Spent (seconds)": 816,
    "Number of People": 1,
    "Activity": "WhatsApp Messenger Android",
    "Category": "Instant Message",
    "Productivity": -1
  },
  {
    "Rank": 3,
    "Time Spent (seconds)": 600,
    "Number of People": 1,
    "Activity": "Samsung Touchwiz Launcher",
    "Category": "General Utilities",
    "Productivity": 1
  },
  {
    "Rank": 4,
    "Time Spent (seconds)": 352,
    "Number of People": 1,
    "Activity": "GMail for Android",
    "Category": "Email",
    "Productivity": 0
  },
  {
    "Rank": 5,
    "Time Spent (seconds)": 108,
    "Number of People": 1,
    "Activity": "mobile - com.sec.android.app.clockpackage",
    "Category": "General Utilities",
    "Productivity": 1
  },
  {
    "Rank": 6,
    "Time Spent (seconds)": 7,
    "Number of People": 1,
    "Activity": "Android Settings",
    "Category": "General Utilities",
    "Productivity": 1
  }
]