[
  {
    "Rank": 1,
    "Time Spent (seconds)": 7281,
    "Number of People": 1,
    "Category": "Entertainment"
  },
  {
    "Rank": 2,
    "Time Spent (seconds)": 5891,
    "Number of People": 1,
    "Category": "Utilities"
  },
  {
    "Rank": 3,
    "Time Spent (seconds)": 2671,
    "Number of People": 1,
    "Category": "Uncategorized"
  },
  {
    "Rank": 4,
    "Time Spent (seconds)": 2287,
    "Number of People": 1,
    "Category": "Business"
  },
  {
    "Rank": 5,
    "Time Spent (seconds)": 2128,
    "Number of People": 1,
    "Category": "Software Development"
  },
  {
    "Rank": 6,
    "Time Spent (seconds)": 1285,
    "Number of People": 1,
    "Category": "Communication & Scheduling"
  },
  {
    "Rank": 7,
    "Time Spent (seconds)": 841,
    "Number of People": 1,
    "Category": "Social Networking"
  },
  {
    "Rank": 8,
    "Time Spent (seconds)": 575,
    "Number of People": 1,
    "Category": "Reference & Learning"
  }
]