{
  "2021-07-4": {
    "Communication & Scheduling": 8771,
    "Uncategorized": 8352,
    "Utilities": 5303,
    "Software Development": 4929,
    "Entertainment": 3023,
    "Business": 2259,
    "Social Networking": 1636,
    "Reference & Learning": 1187,
    "Shopping": 647,
    "Design & Composition": 132,
    "News & Opinion": 26
  },
  "2021-07-5": {
    "Communication & Scheduling": 7521,
    "Uncategorized": 4018,
    "Software Development": 3994,
    "Utilities": 3452,
    "Reference & Learning": 461,
    "Design & Composition": 410,
    "Business": 246,
    "News & Opinion": 193,
    "Shopping": 15,
    "Entertainment": 14,
    "Social Networking": 2
  },
  "2021-07-6": {
    "Software Development": 8970,
    "Utilities": 7902,
    "Communication & Scheduling": 6820,
    "Entertainment": 5059,
    "Uncategorized": 4612,
    "Reference & Learning": 2680,
    "Social Networking": 1506,
    "Business": 135,
    "Design & Composition": 34,
    "Shopping": 7
  },
  "2021-07-7": {
    "Reference & Learning": 5450,
    "Entertainment": 5258,
    "Software Development": 5077,
    "Social Networking": 3409,
    "Uncategorized": 2363,
    "Business": 1736,
    "Utilities": 219,
    "News & Opinion": 74,
    "Design & Composition": 28,
    "Shopping": 7
  },
  "2021-07-8": {},
  "2021-07-9": {},
  "2021-07-10": {}
}