[
  {
    "Rank": 1,
    "Time Spent (seconds)": 1182,
    "Number of People": 1,
    "Activity": "Github",
    "Category": "General Software Development",
    "Productivity": 2
  },
  {
    "Rank": 2,
    "Time Spent (seconds)": 481,
    "Number of People": 1,
    "Activity": "mybluelinux.com",
    "Category": "Uncategorized",
    "Productivity": 0
  },
  {
    "Rank": 3,
    "Time Spent (seconds)": 321,
    "Number of People": 1,
    "Activity": "discourse.gohugo.io",
    "Category": "General Software Development",
    "Productivity": 2
  },
  {
    "Rank": 4,
    "Time Spent (seconds)": 189,
    "Number of People": 1,
    "Activity": "learn.arm.com",
    "Category": "General Reference & Learning",
    "Productivity": 1
  },
  {
    "Rank": 5,
    "Time Spent (seconds)": 112,
    "Number of People": 1,
    "Activity": "lucidmanager.org",
    "Category": "Uncategorized",
    "Productivity": 0
  },
  {
    "Rank": 6,
    "Time Spent (seconds)": 76,
    "Number of People": 1,
    "Activity": "semweb.youronly.one",
    "Category": "Uncategorized",
    "Productivity": 0
  },
  {
    "Rank": 7,
    "Time Spent (seconds)": 66,
    "Number of People": 1,
    "Activity": "jesstruck.dk",
    "Category": "Uncategorized",
    "Productivity": 0
  },
  {
    "Rank": 8,
    "Time Spent (seconds)": 65,
    "Number of People": 1,
    "Activity": "duckduckgo.com",
    "Category": "General Utilities",
    "Productivity": 1
  },
  {
    "Rank": 9,
    "Time Spent (seconds)": 62,
    "Number of People": 1,
    "Activity": "suite8demo.suiteondemand.com",
    "Category": "Uncategorized",
    "Productivity": 0
  },
  {
    "Rank": 10,
    "Time Spent (seconds)": 53,
    "Number of People": 1,
    "Activity": "docs.suitecrm.com",
    "Category": "Uncategorized",
    "Productivity": 0
  },
  {
    "Rank": 11,
    "Time Spent (seconds)": 46,
    "Number of People": 1,
    "Activity": "skcript.com",
    "Category": "Uncategorized",
    "Productivity": 0
  },
  {
    "Rank": 12,
    "Time Spent (seconds)": 40,
    "Number of People": 1,
    "Activity": "hugomods.com",
    "Category": "Uncategorized",
    "Productivity": 0
  },
  {
    "Rank": 13,
    "Time Spent (seconds)": 29,
    "Number of People": 1,
    "Activity": "gift.glenfiddich.com",
    "Category": "Uncategorized",
    "Productivity": 0
  },
  {
    "Rank": 14,
    "Time Spent (seconds)": 13,
    "Number of People": 1,
    "Activity": "arm.com",
    "Category": "General Reference & Learning",
    "Productivity": 1
  },
  {
    "Rank": 15,
    "Time Spent (seconds)": 12,
    "Number of People": 1,
    "Activity": "docs.syncthing.net",
    "Category": "General Reference & Learning",
    "Productivity": 1
  },
  {
    "Rank": 16,
    "Time Spent (seconds)": 12,
    "Number of People": 1,
    "Activity": "afrixi.com",
    "Category": "Uncategorized",
    "Productivity": 0
  },
  {
    "Rank": 17,
    "Time Spent (seconds)": 12,
    "Number of People": 1,
    "Activity": "www-mybluelinux-com.translate.goog",
    "Category": "Uncategorized",
    "Productivity": 0
  },
  {
    "Rank": 18,
    "Time Spent (seconds)": 8,
    "Number of People": 1,
    "Activity": "Google Chrome",
    "Category": "Browsers",
    "Productivity": 0
  },
  {
    "Rank": 19,
    "Time Spent (seconds)": 6,
    "Number of People": 1,
    "Activity": "pgorod.github.io",
    "Category": "General Software Development",
    "Productivity": 2
  },
  {
    "Rank": 20,
    "Time Spent (seconds)": 6,
    "Number of People": 1,
    "Activity": "youtube.com",
    "Category": "Video",
    "Productivity": -2
  },
  {
    "Rank": 21,
    "Time Spent (seconds)": 6,
    "Number of People": 1,
    "Activity": "zzo-docs.vercel.app",
    "Category": "General Software Development",
    "Productivity": 2
  },
  {
    "Rank": 22,
    "Time Spent (seconds)": 6,
    "Number of People": 1,
    "Activity": "suitecrm.com",
    "Category": "Uncategorized",
    "Productivity": 0
  },
  {
    "Rank": 23,
    "Time Spent (seconds)": 4,
    "Number of People": 1,
    "Activity": "readtexts.org",
    "Category": "Uncategorized",
    "Productivity": 0
  }
]