[
  {
    "Rank": 1,
    "Time Spent (seconds)": 2890,
    "Number of People": 1,
    "Category": "Software Development"
  },
  {
    "Rank": 2,
    "Time Spent (seconds)": 1898,
    "Number of People": 1,
    "Category": "Uncategorized"
  },
  {
    "Rank": 3,
    "Time Spent (seconds)": 269,
    "Number of People": 1,
    "Category": "Business"
  },
  {
    "Rank": 4,
    "Time Spent (seconds)": 72,
    "Number of People": 1,
    "Category": "Utilities"
  },
  {
    "Rank": 5,
    "Time Spent (seconds)": 24,
    "Number of People": 1,
    "Category": "Reference & Learning"
  }
]