{
  "2021": {
    "Instant Message": 686053,
    "Browsers": 386122,
    "Intelligence": 16029,
    "General Utilities": 239772,
    "General Shopping": 10324,
    "Uncategorized": 628578,
    "General Reference & Learning": 103509,
    "Video": 122152,
    "Email": 58254,
    "Photos": 367080,
    "Search": 55867,
    "Meetings": 145786,
    "Voice Chat": 5658,
    "General Business": 114048,
    "Presentation": 1759,
    "Writing": 2605,
    "Calendars": 1332,
    "General Communication & Scheduling": 7413,
    "Internet Utilities": 2812,
    "Music": 59973,
    "General Software Development": 418615,
    "General News & Opinion": 25215,
    "Legal & Gov't": 1115,
    "General Design & Composition": 22036,
    "Professional Networking": 41023,
    "Other": 1489,
    "File Sharing": 3841,
    "Engineering & Technology": 58459,
    "Business": 189,
    "Systems Operations": 67857,
    "Editing & IDEs": 43911,
    "Administration": 428,
    "Operations": 1195,
    "Science & Technology": 3634,
    "Quality Assurance": 723,
    "General Social Networking": 22743,
    "Business & Finance": 673,
    "Graphic Design": 12352,
    "General Entertainment": 4074,
    "Comedy": 19,
    "Engineering & Drafting": 17,
    "Customer Relations": 4,
    "Design & Planning": 2057,
    "Project Management": 258,
    "Data Modeling & Analysis": 521,
    "Travel & Outdoors": 239,
    "Health & Medicine": 673,
    "Marketing": 2401,
    "3D Graphic Design": 471,
    "Sales": 5,
    "Employment": 889,
    "Anti-Virus & Spyware": 147,
    "Accounting": 10,
    "Sports": 77,
    "Audio Editing": 40,
    "Video Editing": 51
  }
}