{
  "2021": {
    "Instant Message": 702451,
    "Browsers": 470955,
    "Intelligence": 16481,
    "General Utilities": 271895,
    "General Shopping": 10611,
    "Uncategorized": 725794,
    "General Reference & Learning": 108922,
    "Video": 163689,
    "Email": 61121,
    "Photos": 387524,
    "Search": 60757,
    "Meetings": 145786,
    "Voice Chat": 5807,
    "General Business": 122791,
    "Presentation": 3557,
    "Writing": 3601,
    "Calendars": 1332,
    "General Communication & Scheduling": 7596,
    "Internet Utilities": 2895,
    "Music": 64008,
    "General Software Development": 493996,
    "General News & Opinion": 29396,
    "Legal & Gov't": 1454,
    "General Design & Composition": 29566,
    "Professional Networking": 51533,
    "Other": 1489,
    "File Sharing": 3841,
    "Engineering & Technology": 62849,
    "Business": 189,
    "Systems Operations": 73217,
    "Editing & IDEs": 67452,
    "Administration": 953,
    "Operations": 2064,
    "Science & Technology": 4002,
    "Quality Assurance": 958,
    "General Social Networking": 35268,
    "Business & Finance": 673,
    "Graphic Design": 13127,
    "General Entertainment": 4139,
    "Comedy": 19,
    "Engineering & Drafting": 17,
    "Customer Relations": 4,
    "Design & Planning": 2057,
    "Project Management": 258,
    "Data Modeling & Analysis": 521,
    "Travel & Outdoors": 239,
    "Health & Medicine": 673,
    "Marketing": 2465,
    "3D Graphic Design": 471,
    "Sales": 5,
    "Employment": 1577,
    "Anti-Virus & Spyware": 302,
    "Accounting": 10,
    "Sports": 77,
    "Audio Editing": 40,
    "Video Editing": 51,
    "Society": 26
  }
}