[
  {
    "album": {
      "artists": [
        {
          "external_urls": {
            "spotify": "https://open.spotify.com/artist/1wRPtKGflJrBx9BmLsSwlU"
          },
          "href": "https://api.spotify.com/v1/artists/1wRPtKGflJrBx9BmLsSwlU",
          "id": "1wRPtKGflJrBx9BmLsSwlU",
          "name": "Pritam",
          "type": "artist",
          "uri": "spotify:artist:1wRPtKGflJrBx9BmLsSwlU"
        }
      ],
      "href": "https://api.spotify.com/v1/albums/6IXfWhC7omotM4lt0ROmEr",
      "images": [
        {
          "height": 640,
          "url": "https://i.scdn.co/image/ab67616d0000b273095191f6b96fd9eff585befc",
          "width": 640
        },
        {
          "height": 300,
          "url": "https://i.scdn.co/image/ab67616d00001e02095191f6b96fd9eff585befc",
          "width": 300
        },
        {
          "height": 64,
          "url": "https://i.scdn.co/image/ab67616d00004851095191f6b96fd9eff585befc",
          "width": 64
        }
      ],
      "name": "Love Aaj Kal (Original Motion Picture Soundtrack)",
      "release_date": "2020-02-14",
      "release_date_precision": "day",
      "total_tracks": 11,
      "type": "album",
      "uri": "spotify:album:6IXfWhC7omotM4lt0ROmEr"
    },
    "artists": [
      {
        "external_urls": {
          "spotify": "https://open.spotify.com/artist/1wRPtKGflJrBx9BmLsSwlU"
        },
        "href": "https://api.spotify.com/v1/artists/1wRPtKGflJrBx9BmLsSwlU",
        "id": "1wRPtKGflJrBx9BmLsSwlU",
        "name": "Pritam",
        "type": "artist",
        "uri": "spotify:artist:1wRPtKGflJrBx9BmLsSwlU"
      },
      {
        "external_urls": {
          "spotify": "https://open.spotify.com/artist/2GoeZ0qOTt6kjsWW4eA6LS"
        },
        "href": "https://api.spotify.com/v1/artists/2GoeZ0qOTt6kjsWW4eA6LS",
        "id": "2GoeZ0qOTt6kjsWW4eA6LS",
        "name": "Darshan Raval",
        "type": "artist",
        "uri": "spotify:artist:2GoeZ0qOTt6kjsWW4eA6LS"
      },
      {
        "external_urls": {
          "spotify": "https://open.spotify.com/artist/2UwDJeoMqYers5Jmm75zm2"
        },
        "href": "https://api.spotify.com/v1/artists/2UwDJeoMqYers5Jmm75zm2",
        "id": "2UwDJeoMqYers5Jmm75zm2",
        "name": "Antara Mitra",
        "type": "artist",
        "uri": "spotify:artist:2UwDJeoMqYers5Jmm75zm2"
      }
    ],
    "explicit": false,
    "href": "https://api.spotify.com/v1/tracks/6cUOiOY5qh2FpIQWIYAd2h",
    "is_local": false,
    "name": "Mehrama",
    "preview_url": "https://p.scdn.co/mp3-preview/d0a192ac3f8326b5a8cb70aa0f72446bb8bed96c?cid=811598a754134358878b30bc9c28decd"
  },
  {
    "album": {
      "artists": [
        {
          "external_urls": {
            "spotify": "https://open.spotify.com/artist/0LyfQWJT6nXafLPZqxe9Of"
          },
          "href": "https://api.spotify.com/v1/artists/0LyfQWJT6nXafLPZqxe9Of",
          "id": "0LyfQWJT6nXafLPZqxe9Of",
          "name": "Various Artists",
          "type": "artist",
          "uri": "spotify:artist:0LyfQWJT6nXafLPZqxe9Of"
        }
      ],
      "href": "https://api.spotify.com/v1/albums/2ifXB65SLpF97vWZjKGpQ9",
      "images": [
        {
          "height": 640,
          "url": "https://i.scdn.co/image/ab67616d0000b273e4c77dc1b6c85c754f7f136c",
          "width": 640
        },
        {
          "height": 300,
          "url": "https://i.scdn.co/image/ab67616d00001e02e4c77dc1b6c85c754f7f136c",
          "width": 300
        },
        {
          "height": 64,
          "url": "https://i.scdn.co/image/ab67616d00004851e4c77dc1b6c85c754f7f136c",
          "width": 64
        }
      ],
      "name": "Shiddat",
      "release_date": "2021-09-22",
      "release_date_precision": "day",
      "total_tracks": 7,
      "type": "album",
      "uri": "spotify:album:2ifXB65SLpF97vWZjKGpQ9"
    },
    "artists": [
      {
        "external_urls": {
          "spotify": "https://open.spotify.com/artist/3pQ4aA7dkolyjUAMrVScgh"
        },
        "href": "https://api.spotify.com/v1/artists/3pQ4aA7dkolyjUAMrVScgh",
        "id": "3pQ4aA7dkolyjUAMrVScgh",
        "name": "Manan Bhardwaj",
        "type": "artist",
        "uri": "spotify:artist:3pQ4aA7dkolyjUAMrVScgh"
      }
    ],
    "explicit": false,
    "href": "https://api.spotify.com/v1/tracks/4dy4m6vhOY3BcCVp5fdhQQ",
    "is_local": false,
    "name": "Shiddat (Reprise)",
    "preview_url": "https://p.scdn.co/mp3-preview/99338462715c20ddbfcca21a20675962e7a58b3c?cid=811598a754134358878b30bc9c28decd"
  },
  {
    "album": {
      "artists": [
        {
          "external_urls": {
            "spotify": "https://open.spotify.com/artist/0LyfQWJT6nXafLPZqxe9Of"
          },
          "href": "https://api.spotify.com/v1/artists/0LyfQWJT6nXafLPZqxe9Of",
          "id": "0LyfQWJT6nXafLPZqxe9Of",
          "name": "Various Artists",
          "type": "artist",
          "uri": "spotify:artist:0LyfQWJT6nXafLPZqxe9Of"
        }
      ],
      "href": "https://api.spotify.com/v1/albums/6c4nK9brQbmS2Y2ilrvG5H",
      "images": [
        {
          "height": 640,
          "url": "https://i.scdn.co/image/ab67616d0000b2730dc03da31b9a63b84f9e50eb",
          "width": 640
        },
        {
          "height": 300,
          "url": "https://i.scdn.co/image/ab67616d00001e020dc03da31b9a63b84f9e50eb",
          "width": 300
        },
        {
          "height": 64,
          "url": "https://i.scdn.co/image/ab67616d000048510dc03da31b9a63b84f9e50eb",
          "width": 64
        }
      ],
      "name": "Ek Paheli Leela",
      "release_date": "2015-03-10",
      "release_date_precision": "day",
      "total_tracks": 9,
      "type": "album",
      "uri": "spotify:album:6c4nK9brQbmS2Y2ilrvG5H"
    },
    "artists": [
      {
        "external_urls": {
          "spotify": "https://open.spotify.com/artist/3xbeS8ZmDEW7zgEd0IdArM"
        },
        "href": "https://api.spotify.com/v1/artists/3xbeS8ZmDEW7zgEd0IdArM",
        "id": "3xbeS8ZmDEW7zgEd0IdArM",
        "name": "Uzair Jaswal",
        "type": "artist",
        "uri": "spotify:artist:3xbeS8ZmDEW7zgEd0IdArM"
      }
    ],
    "explicit": false,
    "href": "https://api.spotify.com/v1/tracks/3u947zydbp5jVgVNlaRgv4",
    "is_local": false,
    "name": "Tere Bin Nahi Laage (Male Version)",
    "preview_url": "https://p.scdn.co/mp3-preview/a58b4848335649376f179c09a22d02055c1423fe?cid=811598a754134358878b30bc9c28decd"
  },
  {
    "album": {
      "artists": [
        {
          "external_urls": {
            "spotify": "https://open.spotify.com/artist/4YRxDV8wJFPHPTeXepOstw"
          },
          "href": "https://api.spotify.com/v1/artists/4YRxDV8wJFPHPTeXepOstw",
          "id": "4YRxDV8wJFPHPTeXepOstw",
          "name": "Arijit Singh",
          "type": "artist",
          "uri": "spotify:artist:4YRxDV8wJFPHPTeXepOstw"
        },
        {
          "external_urls": {
            "spotify": "https://open.spotify.com/artist/3ZxZ03fj3tXBZHZWzvaLSM"
          },
          "href": "https://api.spotify.com/v1/artists/3ZxZ03fj3tXBZHZWzvaLSM",
          "id": "3ZxZ03fj3tXBZHZWzvaLSM",
          "name": "Neeti Mohan",
          "type": "artist",
          "uri": "spotify:artist:3ZxZ03fj3tXBZHZWzvaLSM"
        },
        {
          "external_urls": {
            "spotify": "https://open.spotify.com/artist/5r2baeTwcCJnuIsDIlxUJo"
          },
          "href": "https://api.spotify.com/v1/artists/5r2baeTwcCJnuIsDIlxUJo",
          "id": "5r2baeTwcCJnuIsDIlxUJo",
          "name": "Rashmi Virag",
          "type": "artist",
          "uri": "spotify:artist:5r2baeTwcCJnuIsDIlxUJo"
        }
      ],
      "href": "https://api.spotify.com/v1/albums/1XO82yE4raeQEBSHxrNuSe",
      "images": [
        {
          "height": 640,
          "url": "https://i.scdn.co/image/ab67616d0000b2733361905e288acb907f181f6a",
          "width": 640
        },
        {
          "height": 300,
          "url": "https://i.scdn.co/image/ab67616d00001e023361905e288acb907f181f6a",
          "width": 300
        },
        {
          "height": 64,
          "url": "https://i.scdn.co/image/ab67616d000048513361905e288acb907f181f6a",
          "width": 64
        }
      ],
      "name": "Mere Yaaraa (From \"Sooryavanshi\")",
      "release_date": "2021-10-27",
      "release_date_precision": "day",
      "total_tracks": 1,
      "type": "album",
      "uri": "spotify:album:1XO82yE4raeQEBSHxrNuSe"
    },
    "artists": [
      {
        "external_urls": {
          "spotify": "https://open.spotify.com/artist/4YRxDV8wJFPHPTeXepOstw"
        },
        "href": "https://api.spotify.com/v1/artists/4YRxDV8wJFPHPTeXepOstw",
        "id": "4YRxDV8wJFPHPTeXepOstw",
        "name": "Arijit Singh",
        "type": "artist",
        "uri": "spotify:artist:4YRxDV8wJFPHPTeXepOstw"
      },
      {
        "external_urls": {
          "spotify": "https://open.spotify.com/artist/3ZxZ03fj3tXBZHZWzvaLSM"
        },
        "href": "https://api.spotify.com/v1/artists/3ZxZ03fj3tXBZHZWzvaLSM",
        "id": "3ZxZ03fj3tXBZHZWzvaLSM",
        "name": "Neeti Mohan",
        "type": "artist",
        "uri": "spotify:artist:3ZxZ03fj3tXBZHZWzvaLSM"
      },
      {
        "external_urls": {
          "spotify": "https://open.spotify.com/artist/5r2baeTwcCJnuIsDIlxUJo"
        },
        "href": "https://api.spotify.com/v1/artists/5r2baeTwcCJnuIsDIlxUJo",
        "id": "5r2baeTwcCJnuIsDIlxUJo",
        "name": "Rashmi Virag",
        "type": "artist",
        "uri": "spotify:artist:5r2baeTwcCJnuIsDIlxUJo"
      }
    ],
    "explicit": false,
    "href": "https://api.spotify.com/v1/tracks/0tpwqQhdfJXRcUDSNRjb9O",
    "is_local": false,
    "name": "Mere Yaaraa (From \"Sooryavanshi\")",
    "preview_url": "https://p.scdn.co/mp3-preview/421618b42b869b54862051b236feb1bda746d4c9?cid=811598a754134358878b30bc9c28decd"
  },
  {
    "album": {
      "artists": [
        {
          "external_urls": {
            "spotify": "https://open.spotify.com/artist/1wmoF73GhlylxwAbn9YGYr"
          },
          "href": "https://api.spotify.com/v1/artists/1wmoF73GhlylxwAbn9YGYr",
          "id": "1wmoF73GhlylxwAbn9YGYr",
          "name": "Prashant Katheriya",
          "type": "artist",
          "uri": "spotify:artist:1wmoF73GhlylxwAbn9YGYr"
        }
      ],
      "href": "https://api.spotify.com/v1/albums/3EvyrQbcYUbye2DxYDhv8b",
      "images": [
        {
          "height": 640,
          "url": "https://i.scdn.co/image/ab67616d0000b27305b6eb73376a6d9b200450d9",
          "width": 640
        },
        {
          "height": 300,
          "url": "https://i.scdn.co/image/ab67616d00001e0205b6eb73376a6d9b200450d9",
          "width": 300
        },
        {
          "height": 64,
          "url": "https://i.scdn.co/image/ab67616d0000485105b6eb73376a6d9b200450d9",
          "width": 64
        }
      ],
      "name": "Dreams Revisited (Short Version)",
      "release_date": "2022-09-02",
      "release_date_precision": "day",
      "total_tracks": 9,
      "type": "album",
      "uri": "spotify:album:3EvyrQbcYUbye2DxYDhv8b"
    },
    "artists": [
      {
        "external_urls": {
          "spotify": "https://open.spotify.com/artist/1wmoF73GhlylxwAbn9YGYr"
        },
        "href": "https://api.spotify.com/v1/artists/1wmoF73GhlylxwAbn9YGYr",
        "id": "1wmoF73GhlylxwAbn9YGYr",
        "name": "Prashant Katheriya",
        "type": "artist",
        "uri": "spotify:artist:1wmoF73GhlylxwAbn9YGYr"
      }
    ],
    "explicit": false,
    "href": "https://api.spotify.com/v1/tracks/2TcRvzS7C22LePsokUOHnn",
    "is_local": false,
    "name": "Jiske Aane Se Mukammal",
    "preview_url": "https://p.scdn.co/mp3-preview/b14d72e08dcf6ca7ff9ef971f1f9a77c801697a6?cid=811598a754134358878b30bc9c28decd"
  },
  {
    "album": {
      "artists": [
        {
          "external_urls": {
            "spotify": "https://open.spotify.com/artist/2GoeZ0qOTt6kjsWW4eA6LS"
          },
          "href": "https://api.spotify.com/v1/artists/2GoeZ0qOTt6kjsWW4eA6LS",
          "id": "2GoeZ0qOTt6kjsWW4eA6LS",
          "name": "Darshan Raval",
          "type": "artist",
          "uri": "spotify:artist:2GoeZ0qOTt6kjsWW4eA6LS"
        }
      ],
      "href": "https://api.spotify.com/v1/albums/0dUZaBEeoXNmy6wL2M3r0c",
      "images": [
        {
          "height": 640,
          "url": "https://i.scdn.co/image/ab67616d0000b273d47204a03807a0456e8bc2ca",
          "width": 640
        },
        {
          "height": 300,
          "url": "https://i.scdn.co/image/ab67616d00001e02d47204a03807a0456e8bc2ca",
          "width": 300
        },
        {
          "height": 64,
          "url": "https://i.scdn.co/image/ab67616d00004851d47204a03807a0456e8bc2ca",
          "width": 64
        }
      ],
      "name": "Hawa Banke",
      "release_date": "2019-07-18",
      "release_date_precision": "day",
      "total_tracks": 1,
      "type": "album",
      "uri": "spotify:album:0dUZaBEeoXNmy6wL2M3r0c"
    },
    "artists": [
      {
        "external_urls": {
          "spotify": "https://open.spotify.com/artist/2GoeZ0qOTt6kjsWW4eA6LS"
        },
        "href": "https://api.spotify.com/v1/artists/2GoeZ0qOTt6kjsWW4eA6LS",
        "id": "2GoeZ0qOTt6kjsWW4eA6LS",
        "name": "Darshan Raval",
        "type": "artist",
        "uri": "spotify:artist:2GoeZ0qOTt6kjsWW4eA6LS"
      }
    ],
    "explicit": false,
    "href": "https://api.spotify.com/v1/tracks/1L3Nsi7YXtBxTdnbqektia",
    "is_local": false,
    "name": "Hawa Banke",
    "preview_url": "https://p.scdn.co/mp3-preview/52addd154bf9705dd1c4035c170ef8e242ae217d?cid=811598a754134358878b30bc9c28decd"
  },
  {
    "album": {
      "artists": [
        {
          "external_urls": {
            "spotify": "https://open.spotify.com/artist/0LyfQWJT6nXafLPZqxe9Of"
          },
          "href": "https://api.spotify.com/v1/artists/0LyfQWJT6nXafLPZqxe9Of",
          "id": "0LyfQWJT6nXafLPZqxe9Of",
          "name": "Various Artists",
          "type": "artist",
          "uri": "spotify:artist:0LyfQWJT6nXafLPZqxe9Of"
        }
      ],
      "href": "https://api.spotify.com/v1/albums/5BLwx5IlfoWOrjJJ3i7gbK",
      "images": [
        {
          "height": 640,
          "url": "https://i.scdn.co/image/ab67616d0000b273ab827cdec4b3fc1b02bfdb1e",
          "width": 640
        },
        {
          "height": 300,
          "url": "https://i.scdn.co/image/ab67616d00001e02ab827cdec4b3fc1b02bfdb1e",
          "width": 300
        },
        {
          "height": 64,
          "url": "https://i.scdn.co/image/ab67616d00004851ab827cdec4b3fc1b02bfdb1e",
          "width": 64
        }
      ],
      "name": "Shershaah (Original Motion Picture Soundtrack)",
      "release_date": "2021-08-16",
      "release_date_precision": "day",
      "total_tracks": 6,
      "type": "album",
      "uri": "spotify:album:5BLwx5IlfoWOrjJJ3i7gbK"
    },
    "artists": [
      {
        "external_urls": {
          "spotify": "https://open.spotify.com/artist/2zvJLk0gTH7r7A5Q6X5Bq8"
        },
        "href": "https://api.spotify.com/v1/artists/2zvJLk0gTH7r7A5Q6X5Bq8",
        "id": "2zvJLk0gTH7r7A5Q6X5Bq8",
        "name": "Javed-Mohsin",
        "type": "artist",
        "uri": "spotify:artist:2zvJLk0gTH7r7A5Q6X5Bq8"
      },
      {
        "external_urls": {
          "spotify": "https://open.spotify.com/artist/2GoeZ0qOTt6kjsWW4eA6LS"
        },
        "href": "https://api.spotify.com/v1/artists/2GoeZ0qOTt6kjsWW4eA6LS",
        "id": "2GoeZ0qOTt6kjsWW4eA6LS",
        "name": "Darshan Raval",
        "type": "artist",
        "uri": "spotify:artist:2GoeZ0qOTt6kjsWW4eA6LS"
      }
    ],
    "explicit": false,
    "href": "https://api.spotify.com/v1/tracks/6Sflud15ff1KqBzg6wj78S",
    "is_local": false,
    "name": "Kabhii Tumhhe",
    "preview_url": "https://p.scdn.co/mp3-preview/c0e59caa7befa9a9e1898d6b352339abf889c885?cid=811598a754134358878b30bc9c28decd"
  },
  {
    "album": {
      "artists": [
        {
          "external_urls": {
            "spotify": "https://open.spotify.com/artist/3yMmYEklQ7gLOZXEFNd3xr"
          },
          "href": "https://api.spotify.com/v1/artists/3yMmYEklQ7gLOZXEFNd3xr",
          "id": "3yMmYEklQ7gLOZXEFNd3xr",
          "name": "Palak Muchhal",
          "type": "artist",
          "uri": "spotify:artist:3yMmYEklQ7gLOZXEFNd3xr"
        }
      ],
      "href": "https://api.spotify.com/v1/albums/4dYNdtPc5EUSmKtyZ9x0l0",
      "images": [
        {
          "height": 640,
          "url": "https://i.scdn.co/image/ab67616d0000b273808542d48ec7021a0577f4f5",
          "width": 640
        },
        {
          "height": 300,
          "url": "https://i.scdn.co/image/ab67616d00001e02808542d48ec7021a0577f4f5",
          "width": 300
        },
        {
          "height": 64,
          "url": "https://i.scdn.co/image/ab67616d00004851808542d48ec7021a0577f4f5",
          "width": 64
        }
      ],
      "name": "Best Of Palak Muchhal",
      "release_date": "2020-06-09",
      "release_date_precision": "day",
      "total_tracks": 8,
      "type": "album",
      "uri": "spotify:album:4dYNdtPc5EUSmKtyZ9x0l0"
    },
    "artists": [
      {
        "external_urls": {
          "spotify": "https://open.spotify.com/artist/3yMmYEklQ7gLOZXEFNd3xr"
        },
        "href": "https://api.spotify.com/v1/artists/3yMmYEklQ7gLOZXEFNd3xr",
        "id": "3yMmYEklQ7gLOZXEFNd3xr",
        "name": "Palak Muchhal",
        "type": "artist",
        "uri": "spotify:artist:3yMmYEklQ7gLOZXEFNd3xr"
      },
      {
        "external_urls": {
          "spotify": "https://open.spotify.com/artist/4YRxDV8wJFPHPTeXepOstw"
        },
        "href": "https://api.spotify.com/v1/artists/4YRxDV8wJFPHPTeXepOstw",
        "id": "4YRxDV8wJFPHPTeXepOstw",
        "name": "Arijit Singh",
        "type": "artist",
        "uri": "spotify:artist:4YRxDV8wJFPHPTeXepOstw"
      }
    ],
    "explicit": false,
    "href": "https://api.spotify.com/v1/tracks/7Imk0IG6S5GA5iYWkjmMW5",
    "is_local": false,
    "name": "Chahun Main Ya Naa (From \"Aashiqui 2\")",
    "preview_url": "https://p.scdn.co/mp3-preview/992138cef9f397b73f52fd31889d8b9917a46568?cid=811598a754134358878b30bc9c28decd"
  },
  {
    "album": {
      "artists": [
        {
          "external_urls": {
            "spotify": "https://open.spotify.com/artist/1wRPtKGflJrBx9BmLsSwlU"
          },
          "href": "https://api.spotify.com/v1/artists/1wRPtKGflJrBx9BmLsSwlU",
          "id": "1wRPtKGflJrBx9BmLsSwlU",
          "name": "Pritam",
          "type": "artist",
          "uri": "spotify:artist:1wRPtKGflJrBx9BmLsSwlU"
        }
      ],
      "href": "https://api.spotify.com/v1/albums/4I39l0YJ7tmSBXZGZamN5E",
      "images": [
        {
          "height": 640,
          "url": "https://i.scdn.co/image/ab67616d0000b273a08a13555e245f7f11aba13f",
          "width": 640
        },
        {
          "height": 300,
          "url": "https://i.scdn.co/image/ab67616d00001e02a08a13555e245f7f11aba13f",
          "width": 300
        },
        {
          "height": 64,
          "url": "https://i.scdn.co/image/ab67616d00004851a08a13555e245f7f11aba13f",
          "width": 64
        }
      ],
      "name": "Jab Harry Met Sejal (Original Motion Picture Soundtrack)",
      "release_date": "2017-08-03",
      "release_date_precision": "day",
      "total_tracks": 13,
      "type": "album",
      "uri": "spotify:album:4I39l0YJ7tmSBXZGZamN5E"
    },
    "artists": [
      {
        "external_urls": {
          "spotify": "https://open.spotify.com/artist/1wRPtKGflJrBx9BmLsSwlU"
        },
        "href": "https://api.spotify.com/v1/artists/1wRPtKGflJrBx9BmLsSwlU",
        "id": "1wRPtKGflJrBx9BmLsSwlU",
        "name": "Pritam",
        "type": "artist",
        "uri": "spotify:artist:1wRPtKGflJrBx9BmLsSwlU"
      },
      {
        "external_urls": {
          "spotify": "https://open.spotify.com/artist/4YRxDV8wJFPHPTeXepOstw"
        },
        "href": "https://api.spotify.com/v1/artists/4YRxDV8wJFPHPTeXepOstw",
        "id": "4YRxDV8wJFPHPTeXepOstw",
        "name": "Arijit Singh",
        "type": "artist",
        "uri": "spotify:artist:4YRxDV8wJFPHPTeXepOstw"
      }
    ],
    "explicit": false,
    "href": "https://api.spotify.com/v1/tracks/0l6g8Z8mqGbGXFOjigYetD",
    "is_local": false,
    "name": "Hawayein",
    "preview_url": "https://p.scdn.co/mp3-preview/7ba96869d2b37d4efce39991782e058b18f3e3f3?cid=811598a754134358878b30bc9c28decd"
  },
  {
    "album": {
      "artists": [
        {
          "external_urls": {
            "spotify": "https://open.spotify.com/artist/3dN9MQpjIyNxyeRfz4EDZe"
          },
          "href": "https://api.spotify.com/v1/artists/3dN9MQpjIyNxyeRfz4EDZe",
          "id": "3dN9MQpjIyNxyeRfz4EDZe",
          "name": "Rochak Kohli",
          "type": "artist",
          "uri": "spotify:artist:3dN9MQpjIyNxyeRfz4EDZe"
        },
        {
          "external_urls": {
            "spotify": "https://open.spotify.com/artist/4YRxDV8wJFPHPTeXepOstw"
          },
          "href": "https://api.spotify.com/v1/artists/4YRxDV8wJFPHPTeXepOstw",
          "id": "4YRxDV8wJFPHPTeXepOstw",
          "name": "Arijit Singh",
          "type": "artist",
          "uri": "spotify:artist:4YRxDV8wJFPHPTeXepOstw"
        },
        {
          "external_urls": {
            "spotify": "https://open.spotify.com/artist/5f4QpKfy7ptCHwTqspnSJI"
          },
          "href": "https://api.spotify.com/v1/artists/5f4QpKfy7ptCHwTqspnSJI",
          "id": "5f4QpKfy7ptCHwTqspnSJI",
          "name": "Neha Kakkar",
          "type": "artist",
          "uri": "spotify:artist:5f4QpKfy7ptCHwTqspnSJI"
        }
      ],
      "href": "https://api.spotify.com/v1/albums/7aJiY5GW8uSpZItQXcmeVM",
      "images": [
        {
          "height": 640,
          "url": "https://i.scdn.co/image/ab67616d0000b2739c48ffd6b1a9a43b9a74c66c",
          "width": 640
        },
        {
          "height": 300,
          "url": "https://i.scdn.co/image/ab67616d00001e029c48ffd6b1a9a43b9a74c66c",
          "width": 300
        },
        {
          "height": 64,
          "url": "https://i.scdn.co/image/ab67616d000048519c48ffd6b1a9a43b9a74c66c",
          "width": 64
        }
      ],
      "name": "Tu Hi Yaar Mera (From \"Pati Patni Aur Woh\")",
      "release_date": "2019-12-02",
      "release_date_precision": "day",
      "total_tracks": 1,
      "type": "album",
      "uri": "spotify:album:7aJiY5GW8uSpZItQXcmeVM"
    },
    "artists": [
      {
        "external_urls": {
          "spotify": "https://open.spotify.com/artist/3dN9MQpjIyNxyeRfz4EDZe"
        },
        "href": "https://api.spotify.com/v1/artists/3dN9MQpjIyNxyeRfz4EDZe",
        "id": "3dN9MQpjIyNxyeRfz4EDZe",
        "name": "Rochak Kohli",
        "type": "artist",
        "uri": "spotify:artist:3dN9MQpjIyNxyeRfz4EDZe"
      },
      {
        "external_urls": {
          "spotify": "https://open.spotify.com/artist/4YRxDV8wJFPHPTeXepOstw"
        },
        "href": "https://api.spotify.com/v1/artists/4YRxDV8wJFPHPTeXepOstw",
        "id": "4YRxDV8wJFPHPTeXepOstw",
        "name": "Arijit Singh",
        "type": "artist",
        "uri": "spotify:artist:4YRxDV8wJFPHPTeXepOstw"
      },
      {
        "external_urls": {
          "spotify": "https://open.spotify.com/artist/5f4QpKfy7ptCHwTqspnSJI"
        },
        "href": "https://api.spotify.com/v1/artists/5f4QpKfy7ptCHwTqspnSJI",
        "id": "5f4QpKfy7ptCHwTqspnSJI",
        "name": "Neha Kakkar",
        "type": "artist",
        "uri": "spotify:artist:5f4QpKfy7ptCHwTqspnSJI"
      }
    ],
    "explicit": false,
    "href": "https://api.spotify.com/v1/tracks/57jOEZtoLQK4zF2x55bdkp",
    "is_local": false,
    "name": "Tu Hi Yaar Mera (From \"Pati Patni Aur Woh\")",
    "preview_url": "https://p.scdn.co/mp3-preview/be13643772a32958a7c4d97a8f556552a011fd56?cid=811598a754134358878b30bc9c28decd"
  },
  {
    "album": {
      "artists": [
        {
          "external_urls": {
            "spotify": "https://open.spotify.com/artist/0LyfQWJT6nXafLPZqxe9Of"
          },
          "href": "https://api.spotify.com/v1/artists/0LyfQWJT6nXafLPZqxe9Of",
          "id": "0LyfQWJT6nXafLPZqxe9Of",
          "name": "Various Artists",
          "type": "artist",
          "uri": "spotify:artist:0LyfQWJT6nXafLPZqxe9Of"
        }
      ],
      "href": "https://api.spotify.com/v1/albums/1P8eifMN4WiKEXtptCBwJQ",
      "images": [
        {
          "height": 640,
          "url": "https://i.scdn.co/image/ab67616d0000b27384aa52f0a400ecfd7a30a115",
          "width": 640
        },
        {
          "height": 300,
          "url": "https://i.scdn.co/image/ab67616d00001e0284aa52f0a400ecfd7a30a115",
          "width": 300
        },
        {
          "height": 64,
          "url": "https://i.scdn.co/image/ab67616d0000485184aa52f0a400ecfd7a30a115",
          "width": 64
        }
      ],
      "name": "Bareilly Ki Barfi",
      "release_date": "2017-08-17",
      "release_date_precision": "day",
      "total_tracks": 8,
      "type": "album",
      "uri": "spotify:album:1P8eifMN4WiKEXtptCBwJQ"
    },
    "artists": [
      {
        "external_urls": {
          "spotify": "https://open.spotify.com/artist/7qHsapL39aTQsPhixtzVvy"
        },
        "href": "https://api.spotify.com/v1/artists/7qHsapL39aTQsPhixtzVvy",
        "id": "7qHsapL39aTQsPhixtzVvy",
        "name": "Ayushmann Khurrana",
        "type": "artist",
        "uri": "spotify:artist:7qHsapL39aTQsPhixtzVvy"
      }
    ],
    "explicit": false,
    "href": "https://api.spotify.com/v1/tracks/3FLJR1N1dxOYEpZCsTX8p6",
    "is_local": false,
    "name": "Nazm Nazm feat. Ayushmann Khurana",
    "preview_url": "https://p.scdn.co/mp3-preview/aa64a38b607d8624b7d59641ff5cac499e37f455?cid=811598a754134358878b30bc9c28decd"
  },
  {
    "album": {
      "artists": [
        {
          "external_urls": {
            "spotify": "https://open.spotify.com/artist/0FJz7XR37hH69traaHLijA"
          },
          "href": "https://api.spotify.com/v1/artists/0FJz7XR37hH69traaHLijA",
          "id": "0FJz7XR37hH69traaHLijA",
          "name": "Shaarib Toshi",
          "type": "artist",
          "uri": "spotify:artist:0FJz7XR37hH69traaHLijA"
        }
      ],
      "href": "https://api.spotify.com/v1/albums/0eBjbMAR0N7knX6hBT6c3h",
      "images": [
        {
          "height": 640,
          "url": "https://i.scdn.co/image/ab67616d0000b2735cd31847e786b7e1e185e062",
          "width": 640
        },
        {
          "height": 300,
          "url": "https://i.scdn.co/image/ab67616d00001e025cd31847e786b7e1e185e062",
          "width": 300
        },
        {
          "height": 64,
          "url": "https://i.scdn.co/image/ab67616d000048515cd31847e786b7e1e185e062",
          "width": 64
        }
      ],
      "name": "Bandeya (feat. Arijit Singh) [From \"Dil Juunglee\"]",
      "release_date": "2018-02-22",
      "release_date_precision": "day",
      "total_tracks": 1,
      "type": "album",
      "uri": "spotify:album:0eBjbMAR0N7knX6hBT6c3h"
    },
    "artists": [
      {
        "external_urls": {
          "spotify": "https://open.spotify.com/artist/0FJz7XR37hH69traaHLijA"
        },
        "href": "https://api.spotify.com/v1/artists/0FJz7XR37hH69traaHLijA",
        "id": "0FJz7XR37hH69traaHLijA",
        "name": "Shaarib Toshi",
        "type": "artist",
        "uri": "spotify:artist:0FJz7XR37hH69traaHLijA"
      },
      {
        "external_urls": {
          "spotify": "https://open.spotify.com/artist/4YRxDV8wJFPHPTeXepOstw"
        },
        "href": "https://api.spotify.com/v1/artists/4YRxDV8wJFPHPTeXepOstw",
        "id": "4YRxDV8wJFPHPTeXepOstw",
        "name": "Arijit Singh",
        "type": "artist",
        "uri": "spotify:artist:4YRxDV8wJFPHPTeXepOstw"
      }
    ],
    "explicit": false,
    "href": "https://api.spotify.com/v1/tracks/6gwnKOvdBKkTU4CQ7KpIAu",
    "is_local": false,
    "name": "Bandeya (feat. Arijit Singh) - From \"Dil Juunglee\"",
    "preview_url": "https://p.scdn.co/mp3-preview/0f59260620151041d5539f10446958045aa8a43b?cid=811598a754134358878b30bc9c28decd"
  },
  {
    "album": {
      "artists": [
        {
          "external_urls": {
            "spotify": "https://open.spotify.com/artist/4f7KfxeHq9BiylGmyXepGt"
          },
          "href": "https://api.spotify.com/v1/artists/4f7KfxeHq9BiylGmyXepGt",
          "id": "4f7KfxeHq9BiylGmyXepGt",
          "name": "Tanishk Bagchi",
          "type": "artist",
          "uri": "spotify:artist:4f7KfxeHq9BiylGmyXepGt"
        },
        {
          "external_urls": {
            "spotify": "https://open.spotify.com/artist/4YRxDV8wJFPHPTeXepOstw"
          },
          "href": "https://api.spotify.com/v1/artists/4YRxDV8wJFPHPTeXepOstw",
          "id": "4YRxDV8wJFPHPTeXepOstw",
          "name": "Arijit Singh",
          "type": "artist",
          "uri": "spotify:artist:4YRxDV8wJFPHPTeXepOstw"
        },
        {
          "external_urls": {
            "spotify": "https://open.spotify.com/artist/1sVmXkzX2ukc6QvasrDBES"
          },
          "href": "https://api.spotify.com/v1/artists/1sVmXkzX2ukc6QvasrDBES",
          "id": "1sVmXkzX2ukc6QvasrDBES",
          "name": "Asees Kaur",
          "type": "artist",
          "uri": "spotify:artist:1sVmXkzX2ukc6QvasrDBES"
        }
      ],
      "href": "https://api.spotify.com/v1/albums/0wzJaFTmOlIGokjoNJ9loW",
      "images": [
        {
          "height": 640,
          "url": "https://i.scdn.co/image/ab67616d0000b273f03c4d5b0c0669c7e14dfb24",
          "width": 640
        },
        {
          "height": 300,
          "url": "https://i.scdn.co/image/ab67616d00001e02f03c4d5b0c0669c7e14dfb24",
          "width": 300
        },
        {
          "height": 64,
          "url": "https://i.scdn.co/image/ab67616d00004851f03c4d5b0c0669c7e14dfb24",
          "width": 64
        }
      ],
      "name": "Bolna (From \"Kapoor & Sons (Since 1921)\")",
      "release_date": "2016-03-04",
      "release_date_precision": "day",
      "total_tracks": 1,
      "type": "album",
      "uri": "spotify:album:0wzJaFTmOlIGokjoNJ9loW"
    },
    "artists": [
      {
        "external_urls": {
          "spotify": "https://open.spotify.com/artist/4f7KfxeHq9BiylGmyXepGt"
        },
        "href": "https://api.spotify.com/v1/artists/4f7KfxeHq9BiylGmyXepGt",
        "id": "4f7KfxeHq9BiylGmyXepGt",
        "name": "Tanishk Bagchi",
        "type": "artist",
        "uri": "spotify:artist:4f7KfxeHq9BiylGmyXepGt"
      },
      {
        "external_urls": {
          "spotify": "https://open.spotify.com/artist/4YRxDV8wJFPHPTeXepOstw"
        },
        "href": "https://api.spotify.com/v1/artists/4YRxDV8wJFPHPTeXepOstw",
        "id": "4YRxDV8wJFPHPTeXepOstw",
        "name": "Arijit Singh",
        "type": "artist",
        "uri": "spotify:artist:4YRxDV8wJFPHPTeXepOstw"
      },
      {
        "external_urls": {
          "spotify": "https://open.spotify.com/artist/1sVmXkzX2ukc6QvasrDBES"
        },
        "href": "https://api.spotify.com/v1/artists/1sVmXkzX2ukc6QvasrDBES",
        "id": "1sVmXkzX2ukc6QvasrDBES",
        "name": "Asees Kaur",
        "type": "artist",
        "uri": "spotify:artist:1sVmXkzX2ukc6QvasrDBES"
      }
    ],
    "explicit": false,
    "href": "https://api.spotify.com/v1/tracks/3GrCQPpKqKzOcKfMAoqn82",
    "is_local": false,
    "name": "Bolna (From \"Kapoor & Sons (Since 1921)\")",
    "preview_url": "https://p.scdn.co/mp3-preview/ca84dbbe1e5a6ada84a6162298f2e8a988135edc?cid=811598a754134358878b30bc9c28decd"
  },
  {
    "album": {
      "artists": [
        {
          "external_urls": {
            "spotify": "https://open.spotify.com/artist/7HCqGPJcQTyGJ2yqntbuyr"
          },
          "href": "https://api.spotify.com/v1/artists/7HCqGPJcQTyGJ2yqntbuyr",
          "id": "7HCqGPJcQTyGJ2yqntbuyr",
          "name": "Amit Trivedi",
          "type": "artist",
          "uri": "spotify:artist:7HCqGPJcQTyGJ2yqntbuyr"
        }
      ],
      "href": "https://api.spotify.com/v1/albums/7lF34sP6HtRAL7VEMvYHff",
      "images": [
        {
          "height": 640,
          "url": "https://i.scdn.co/image/ab67616d0000b2738c72151621d5c60ed768d010",
          "width": 640
        },
        {
          "height": 300,
          "url": "https://i.scdn.co/image/ab67616d00001e028c72151621d5c60ed768d010",
          "width": 300
        },
        {
          "height": 64,
          "url": "https://i.scdn.co/image/ab67616d000048518c72151621d5c60ed768d010",
          "width": 64
        }
      ],
      "name": "Kedarnath",
      "release_date": "2018-11-27",
      "release_date_precision": "day",
      "total_tracks": 5,
      "type": "album",
      "uri": "spotify:album:7lF34sP6HtRAL7VEMvYHff"
    },
    "artists": [
      {
        "external_urls": {
          "spotify": "https://open.spotify.com/artist/4YRxDV8wJFPHPTeXepOstw"
        },
        "href": "https://api.spotify.com/v1/artists/4YRxDV8wJFPHPTeXepOstw",
        "id": "4YRxDV8wJFPHPTeXepOstw",
        "name": "Arijit Singh",
        "type": "artist",
        "uri": "spotify:artist:4YRxDV8wJFPHPTeXepOstw"
      }
    ],
    "explicit": false,
    "href": "https://api.spotify.com/v1/tracks/6pzlnyHTVYi5FOmrgOmC95",
    "is_local": false,
    "name": "Jaan 'Nisaar (Arijit)",
    "preview_url": "https://p.scdn.co/mp3-preview/96bba1ccd77f73e08183ea4c9039af348838f4ff?cid=811598a754134358878b30bc9c28decd"
  },
  {
    "album": {
      "artists": [
        {
          "external_urls": {
            "spotify": "https://open.spotify.com/artist/1wRPtKGflJrBx9BmLsSwlU"
          },
          "href": "https://api.spotify.com/v1/artists/1wRPtKGflJrBx9BmLsSwlU",
          "id": "1wRPtKGflJrBx9BmLsSwlU",
          "name": "Pritam",
          "type": "artist",
          "uri": "spotify:artist:1wRPtKGflJrBx9BmLsSwlU"
        }
      ],
      "href": "https://api.spotify.com/v1/albums/6IXfWhC7omotM4lt0ROmEr",
      "images": [
        {
          "height": 640,
          "url": "https://i.scdn.co/image/ab67616d0000b273095191f6b96fd9eff585befc",
          "width": 640
        },
        {
          "height": 300,
          "url": "https://i.scdn.co/image/ab67616d00001e02095191f6b96fd9eff585befc",
          "width": 300
        },
        {
          "height": 64,
          "url": "https://i.scdn.co/image/ab67616d00004851095191f6b96fd9eff585befc",
          "width": 64
        }
      ],
      "name": "Love Aaj Kal (Original Motion Picture Soundtrack)",
      "release_date": "2020-02-14",
      "release_date_precision": "day",
      "total_tracks": 11,
      "type": "album",
      "uri": "spotify:album:6IXfWhC7omotM4lt0ROmEr"
    },
    "artists": [
      {
        "external_urls": {
          "spotify": "https://open.spotify.com/artist/1wRPtKGflJrBx9BmLsSwlU"
        },
        "href": "https://api.spotify.com/v1/artists/1wRPtKGflJrBx9BmLsSwlU",
        "id": "1wRPtKGflJrBx9BmLsSwlU",
        "name": "Pritam",
        "type": "artist",
        "uri": "spotify:artist:1wRPtKGflJrBx9BmLsSwlU"
      },
      {
        "external_urls": {
          "spotify": "https://open.spotify.com/artist/4YRxDV8wJFPHPTeXepOstw"
        },
        "href": "https://api.spotify.com/v1/artists/4YRxDV8wJFPHPTeXepOstw",
        "id": "4YRxDV8wJFPHPTeXepOstw",
        "name": "Arijit Singh",
        "type": "artist",
        "uri": "spotify:artist:4YRxDV8wJFPHPTeXepOstw"
      }
    ],
    "explicit": false,
    "href": "https://api.spotify.com/v1/tracks/1smFN2CLqGROu0J0UyvDfL",
    "is_local": false,
    "name": "Shayad",
    "preview_url": "https://p.scdn.co/mp3-preview/32b5d7af29bfb04b7f97294f192f81892a5ce14f?cid=811598a754134358878b30bc9c28decd"
  },
  {
    "album": {
      "artists": [
        {
          "external_urls": {
            "spotify": "https://open.spotify.com/artist/3dN9MQpjIyNxyeRfz4EDZe"
          },
          "href": "https://api.spotify.com/v1/artists/3dN9MQpjIyNxyeRfz4EDZe",
          "id": "3dN9MQpjIyNxyeRfz4EDZe",
          "name": "Rochak Kohli",
          "type": "artist",
          "uri": "spotify:artist:3dN9MQpjIyNxyeRfz4EDZe"
        },
        {
          "external_urls": {
            "spotify": "https://open.spotify.com/artist/2oSONSC9zQ4UonDKnLqksx"
          },
          "href": "https://api.spotify.com/v1/artists/2oSONSC9zQ4UonDKnLqksx",
          "id": "2oSONSC9zQ4UonDKnLqksx",
          "name": "Atif Aslam",
          "type": "artist",
          "uri": "spotify:artist:2oSONSC9zQ4UonDKnLqksx"
        },
        {
          "external_urls": {
            "spotify": "https://open.spotify.com/artist/0T1CMVkqffHlqEk4BcAph1"
          },
          "href": "https://api.spotify.com/v1/artists/0T1CMVkqffHlqEk4BcAph1",
          "id": "0T1CMVkqffHlqEk4BcAph1",
          "name": "Tulsi Kumar",
          "type": "artist",
          "uri": "spotify:artist:0T1CMVkqffHlqEk4BcAph1"
        }
      ],
      "href": "https://api.spotify.com/v1/albums/6JsjTQo1PrSQSe7ENpUwXu",
      "images": [
        {
          "height": 640,
          "url": "https://i.scdn.co/image/ab67616d0000b2739742672a11faf728dea4b1cd",
          "width": 640
        },
        {
          "height": 300,
          "url": "https://i.scdn.co/image/ab67616d00001e029742672a11faf728dea4b1cd",
          "width": 300
        },
        {
          "height": 64,
          "url": "https://i.scdn.co/image/ab67616d000048519742672a11faf728dea4b1cd",
          "width": 64
        }
      ],
      "name": "Paniyon Sa (From \"Satyameva Jayate\")",
      "release_date": "2018-07-12",
      "release_date_precision": "day",
      "total_tracks": 1,
      "type": "album",
      "uri": "spotify:album:6JsjTQo1PrSQSe7ENpUwXu"
    },
    "artists": [
      {
        "external_urls": {
          "spotify": "https://open.spotify.com/artist/3dN9MQpjIyNxyeRfz4EDZe"
        },
        "href": "https://api.spotify.com/v1/artists/3dN9MQpjIyNxyeRfz4EDZe",
        "id": "3dN9MQpjIyNxyeRfz4EDZe",
        "name": "Rochak Kohli",
        "type": "artist",
        "uri": "spotify:artist:3dN9MQpjIyNxyeRfz4EDZe"
      },
      {
        "external_urls": {
          "spotify": "https://open.spotify.com/artist/2oSONSC9zQ4UonDKnLqksx"
        },
        "href": "https://api.spotify.com/v1/artists/2oSONSC9zQ4UonDKnLqksx",
        "id": "2oSONSC9zQ4UonDKnLqksx",
        "name": "Atif Aslam",
        "type": "artist",
        "uri": "spotify:artist:2oSONSC9zQ4UonDKnLqksx"
      },
      {
        "external_urls": {
          "spotify": "https://open.spotify.com/artist/0T1CMVkqffHlqEk4BcAph1"
        },
        "href": "https://api.spotify.com/v1/artists/0T1CMVkqffHlqEk4BcAph1",
        "id": "0T1CMVkqffHlqEk4BcAph1",
        "name": "Tulsi Kumar",
        "type": "artist",
        "uri": "spotify:artist:0T1CMVkqffHlqEk4BcAph1"
      }
    ],
    "explicit": false,
    "href": "https://api.spotify.com/v1/tracks/2si0ZNx4yRbggTvrIom8A2",
    "is_local": false,
    "name": "Paniyon Sa",
    "preview_url": "https://p.scdn.co/mp3-preview/15d2e144d0b413b9c01fd6cec10a9e6f90882b56?cid=811598a754134358878b30bc9c28decd"
  },
  {
    "album": {
      "artists": [
        {
          "external_urls": {
            "spotify": "https://open.spotify.com/artist/2kkQthS9OLpK4UqNWYqoVl"
          },
          "href": "https://api.spotify.com/v1/artists/2kkQthS9OLpK4UqNWYqoVl",
          "id": "2kkQthS9OLpK4UqNWYqoVl",
          "name": "Jeet Gannguli",
          "type": "artist",
          "uri": "spotify:artist:2kkQthS9OLpK4UqNWYqoVl"
        },
        {
          "external_urls": {
            "spotify": "https://open.spotify.com/artist/09UmIX92EUH9hAK4bxvHx6"
          },
          "href": "https://api.spotify.com/v1/artists/09UmIX92EUH9hAK4bxvHx6",
          "id": "09UmIX92EUH9hAK4bxvHx6",
          "name": "Mithoon",
          "type": "artist",
          "uri": "spotify:artist:09UmIX92EUH9hAK4bxvHx6"
        },
        {
          "external_urls": {
            "spotify": "https://open.spotify.com/artist/5ugsiK49gIkIVh8U93EO0z"
          },
          "href": "https://api.spotify.com/v1/artists/5ugsiK49gIkIVh8U93EO0z",
          "id": "5ugsiK49gIkIVh8U93EO0z",
          "name": "Ami Mishra",
          "type": "artist",
          "uri": "spotify:artist:5ugsiK49gIkIVh8U93EO0z"
        }
      ],
      "href": "https://api.spotify.com/v1/albums/7sVzilmsqYcLMYw2gtvoZM",
      "images": [
        {
          "height": 640,
          "url": "https://i.scdn.co/image/ab67616d0000b273b0f9ceb59927ab76fe6269be",
          "width": 640
        },
        {
          "height": 300,
          "url": "https://i.scdn.co/image/ab67616d00001e02b0f9ceb59927ab76fe6269be",
          "width": 300
        },
        {
          "height": 64,
          "url": "https://i.scdn.co/image/ab67616d00004851b0f9ceb59927ab76fe6269be",
          "width": 64
        }
      ],
      "name": "Hamari Adhuri Kahani (Original Motion Picture Soundtrack)",
      "release_date": "2015-05-21",
      "release_date_precision": "day",
      "total_tracks": 6,
      "type": "album",
      "uri": "spotify:album:7sVzilmsqYcLMYw2gtvoZM"
    },
    "artists": [
      {
        "external_urls": {
          "spotify": "https://open.spotify.com/artist/5ugsiK49gIkIVh8U93EO0z"
        },
        "href": "https://api.spotify.com/v1/artists/5ugsiK49gIkIVh8U93EO0z",
        "id": "5ugsiK49gIkIVh8U93EO0z",
        "name": "Ami Mishra",
        "type": "artist",
        "uri": "spotify:artist:5ugsiK49gIkIVh8U93EO0z"
      },
      {
        "external_urls": {
          "spotify": "https://open.spotify.com/artist/0oOet2f43PA68X5RxKobEy"
        },
        "href": "https://api.spotify.com/v1/artists/0oOet2f43PA68X5RxKobEy",
        "id": "0oOet2f43PA68X5RxKobEy",
        "name": "Shreya Ghoshal",
        "type": "artist",
        "uri": "spotify:artist:0oOet2f43PA68X5RxKobEy"
      }
    ],
    "explicit": false,
    "href": "https://api.spotify.com/v1/tracks/1cmZbGkCEVVAck2MsWpPYQ",
    "is_local": false,
    "name": "Hasi - Female Version",
    "preview_url": "https://p.scdn.co/mp3-preview/28e4dc1f43006e71f27efafc3b6e78f5fbf42079?cid=811598a754134358878b30bc9c28decd"
  },
  {
    "album": {
      "artists": [
        {
          "external_urls": {
            "spotify": "https://open.spotify.com/artist/1mBydYMVBECdDmMfE2sEUO"
          },
          "href": "https://api.spotify.com/v1/artists/1mBydYMVBECdDmMfE2sEUO",
          "id": "1mBydYMVBECdDmMfE2sEUO",
          "name": "Sachin-Jigar",
          "type": "artist",
          "uri": "spotify:artist:1mBydYMVBECdDmMfE2sEUO"
        }
      ],
      "href": "https://api.spotify.com/v1/albums/4ahg47diWPOQ6d6C8e6PHI",
      "images": [
        {
          "height": 640,
          "url": "https://i.scdn.co/image/ab67616d0000b2736e5e8162fe8fe0931130696e",
          "width": 640
        },
        {
          "height": 300,
          "url": "https://i.scdn.co/image/ab67616d00001e026e5e8162fe8fe0931130696e",
          "width": 300
        },
        {
          "height": 64,
          "url": "https://i.scdn.co/image/ab67616d000048516e5e8162fe8fe0931130696e",
          "width": 64
        }
      ],
      "name": "Badlapur (Original Motion Picture Soundtrack)",
      "release_date": "2014-12-09",
      "release_date_precision": "day",
      "total_tracks": 8,
      "type": "album",
      "uri": "spotify:album:4ahg47diWPOQ6d6C8e6PHI"
    },
    "artists": [
      {
        "external_urls": {
          "spotify": "https://open.spotify.com/artist/2oSONSC9zQ4UonDKnLqksx"
        },
        "href": "https://api.spotify.com/v1/artists/2oSONSC9zQ4UonDKnLqksx",
        "id": "2oSONSC9zQ4UonDKnLqksx",
        "name": "Atif Aslam",
        "type": "artist",
        "uri": "spotify:artist:2oSONSC9zQ4UonDKnLqksx"
      }
    ],
    "explicit": false,
    "href": "https://api.spotify.com/v1/tracks/2GXXZFUxYg2LvG8SR0byOE",
    "is_local": false,
    "name": "Jeena Jeena",
    "preview_url": "https://p.scdn.co/mp3-preview/a03fea2a32d16515ab8209cd6aad3c164ead18fd?cid=811598a754134358878b30bc9c28decd"
  },
  {
    "album": {
      "artists": [
        {
          "external_urls": {
            "spotify": "https://open.spotify.com/artist/0LyfQWJT6nXafLPZqxe9Of"
          },
          "href": "https://api.spotify.com/v1/artists/0LyfQWJT6nXafLPZqxe9Of",
          "id": "0LyfQWJT6nXafLPZqxe9Of",
          "name": "Various Artists",
          "type": "artist",
          "uri": "spotify:artist:0LyfQWJT6nXafLPZqxe9Of"
        }
      ],
      "href": "https://api.spotify.com/v1/albums/1TK8mLZQbWPe4sRmkcWrIu",
      "images": [
        {
          "height": 640,
          "url": "https://i.scdn.co/image/ab67616d0000b273c202064e0775440dacef8802",
          "width": 640
        },
        {
          "height": 300,
          "url": "https://i.scdn.co/image/ab67616d00001e02c202064e0775440dacef8802",
          "width": 300
        },
        {
          "height": 64,
          "url": "https://i.scdn.co/image/ab67616d00004851c202064e0775440dacef8802",
          "width": 64
        }
      ],
      "name": "Rustom (Original Motion Picture Soundtrack)",
      "release_date": "2016-07-15",
      "release_date_precision": "day",
      "total_tracks": 11,
      "type": "album",
      "uri": "spotify:album:1TK8mLZQbWPe4sRmkcWrIu"
    },
    "artists": [
      {
        "external_urls": {
          "spotify": "https://open.spotify.com/artist/4YRxDV8wJFPHPTeXepOstw"
        },
        "href": "https://api.spotify.com/v1/artists/4YRxDV8wJFPHPTeXepOstw",
        "id": "4YRxDV8wJFPHPTeXepOstw",
        "name": "Arijit Singh",
        "type": "artist",
        "uri": "spotify:artist:4YRxDV8wJFPHPTeXepOstw"
      },
      {
        "external_urls": {
          "spotify": "https://open.spotify.com/artist/3yMmYEklQ7gLOZXEFNd3xr"
        },
        "href": "https://api.spotify.com/v1/artists/3yMmYEklQ7gLOZXEFNd3xr",
        "id": "3yMmYEklQ7gLOZXEFNd3xr",
        "name": "Palak Muchhal",
        "type": "artist",
        "uri": "spotify:artist:3yMmYEklQ7gLOZXEFNd3xr"
      },
      {
        "external_urls": {
          "spotify": "https://open.spotify.com/artist/2kkQthS9OLpK4UqNWYqoVl"
        },
        "href": "https://api.spotify.com/v1/artists/2kkQthS9OLpK4UqNWYqoVl",
        "id": "2kkQthS9OLpK4UqNWYqoVl",
        "name": "Jeet Gannguli",
        "type": "artist",
        "uri": "spotify:artist:2kkQthS9OLpK4UqNWYqoVl"
      }
    ],
    "explicit": false,
    "href": "https://api.spotify.com/v1/tracks/7AV1hh76pC1mg4iSH796Vp",
    "is_local": false,
    "name": "Dekha Hazaro Dafaa",
    "preview_url": "https://p.scdn.co/mp3-preview/5d3b08f06768d09aa2cfe012894a5a629ed40f2b?cid=811598a754134358878b30bc9c28decd"
  },
  {
    "album": {
      "artists": [
        {
          "external_urls": {
            "spotify": "https://open.spotify.com/artist/4wwYGgSpeBtvk5WX6HBqzw"
          },
          "href": "https://api.spotify.com/v1/artists/4wwYGgSpeBtvk5WX6HBqzw",
          "id": "4wwYGgSpeBtvk5WX6HBqzw",
          "name": "Aditya A",
          "type": "artist",
          "uri": "spotify:artist:4wwYGgSpeBtvk5WX6HBqzw"
        }
      ],
      "href": "https://api.spotify.com/v1/albums/6AJaDEafyyyWWXHZQtcFGe",
      "images": [
        {
          "height": 640,
          "url": "https://i.scdn.co/image/ab67616d0000b273ec4ecaa0fcf68c0966f21514",
          "width": 640
        },
        {
          "height": 300,
          "url": "https://i.scdn.co/image/ab67616d00001e02ec4ecaa0fcf68c0966f21514",
          "width": 300
        },
        {
          "height": 64,
          "url": "https://i.scdn.co/image/ab67616d00004851ec4ecaa0fcf68c0966f21514",
          "width": 64
        }
      ],
      "name": "Chaand Baaliyan",
      "release_date": "2020-03-28",
      "release_date_precision": "day",
      "total_tracks": 1,
      "type": "album",
      "uri": "spotify:album:6AJaDEafyyyWWXHZQtcFGe"
    },
    "artists": [
      {
        "external_urls": {
          "spotify": "https://open.spotify.com/artist/4wwYGgSpeBtvk5WX6HBqzw"
        },
        "href": "https://api.spotify.com/v1/artists/4wwYGgSpeBtvk5WX6HBqzw",
        "id": "4wwYGgSpeBtvk5WX6HBqzw",
        "name": "Aditya A",
        "type": "artist",
        "uri": "spotify:artist:4wwYGgSpeBtvk5WX6HBqzw"
      }
    ],
    "explicit": false,
    "href": "https://api.spotify.com/v1/tracks/0snQrp1VaY5Pj1YIHRJpRJ",
    "is_local": false,
    "name": "Chaand Baaliyan",
    "preview_url": "https://p.scdn.co/mp3-preview/7b3fa2ce4b001db04e9b70f61d430d12dfde75ce?cid=811598a754134358878b30bc9c28decd"
  }
]