[
  {
    "Rank": 1,
    "Time Spent (seconds)": 5560,
    "Number of People": 1,
    "Category": "Reference & Learning"
  },
  {
    "Rank": 2,
    "Time Spent (seconds)": 4047,
    "Number of People": 1,
    "Category": "Utilities"
  },
  {
    "Rank": 3,
    "Time Spent (seconds)": 3236,
    "Number of People": 1,
    "Category": "Uncategorized"
  },
  {
    "Rank": 4,
    "Time Spent (seconds)": 2381,
    "Number of People": 1,
    "Category": "Entertainment"
  },
  {
    "Rank": 5,
    "Time Spent (seconds)": 2369,
    "Number of People": 1,
    "Category": "Social Networking"
  },
  {
    "Rank": 6,
    "Time Spent (seconds)": 1119,
    "Number of People": 1,
    "Category": "Communication & Scheduling"
  },
  {
    "Rank": 7,
    "Time Spent (seconds)": 236,
    "Number of People": 1,
    "Category": "News & Opinion"
  },
  {
    "Rank": 8,
    "Time Spent (seconds)": 199,
    "Number of People": 1,
    "Category": "Software Development"
  }
]