{
  "2021": {
    "Communication & Scheduling": 1714188,
    "Utilities": 1316871,
    "Business": 398897,
    "Shopping": 28104,
    "Uncategorized": 1101998,
    "Entertainment": 1282363,
    "Reference & Learning": 543395,
    "Design & Composition": 73135,
    "Software Development": 1041611,
    "News & Opinion": 69170,
    "Social Networking": 207797
  },
  "2022": {
    "Software Development": 534514,
    "Uncategorized": 610293,
    "Business": 631454,
    "Communication & Scheduling": 763799,
    "Utilities": 1477898,
    "Entertainment": 1020300,
    "Design & Composition": 80634,
    "Social Networking": 154365,
    "Reference & Learning": 240837,
    "News & Opinion": 32348,
    "Shopping": 94892,
    "Other Work": 12768
  },
  "2023": {
    "Communication & Scheduling": 213295,
    "Utilities": 760165,
    "Design & Composition": 15321,
    "Software Development": 195077,
    "Entertainment": 288628,
    "Uncategorized": 212194,
    "Business": 17100,
    "Shopping": 21682,
    "Social Networking": 67217,
    "Reference & Learning": 64276,
    "News & Opinion": 13016
  }
}